anipy/__init__.py
anipy/core.py
anipy/exception.py
anipy/utils.py
anipy-0.1a1.dist-info/DESCRIPTION.rst
anipy-0.1a1.dist-info/METADATA
anipy-0.1a1.dist-info/RECORD
anipy-0.1a1.dist-info/WHEEL
anipy-0.1a1.dist-info/metadata.json
anipy-0.1a1.dist-info/top_level.txt
