Metadata-Version: 2.0
Name: anipy
Version: 0.1a1
Summary: A python library for the Anilist.co API.
Home-page: https://github.com/twissell-/anipy
Author: Damian Maggio Esne
Author-email: dmaggioesne@gmail.com
License: MIT
Keywords: anipy twissell anime anilist manga
Platform: UNKNOWN
Classifier: Development Status :: 3 - Alpha
Classifier: License :: OSI Approved :: MIT License
Classifier: Programming Language :: Python :: 3.4
Classifier: Programming Language :: Python :: 3.5
Classifier: Topic :: Internet
Classifier: Topic :: Utilities
Requires-Dist: requests
Requires-Dist: urllib3
Requires-Dist: urllib3-mock
